setup.cfg
setup.py
pypushover/__init__.py
pypushover/_base.py
pypushover/client.py
pypushover/groups.py
pypushover/license.py
pypushover/message.py
pypushover/verification.py
pypushover.egg-info/PKG-INFO
pypushover.egg-info/SOURCES.txt
pypushover.egg-info/dependency_links.txt
pypushover.egg-info/requires.txt
pypushover.egg-info/top_level.txt
pypushover/Constants/OS.py
pypushover/Constants/PRIORITIES.py
pypushover/Constants/SOUNDS.py
pypushover/Constants/__init__.py
tests/__init__.py
tests/runtests.py
tests/sandbox.py
tests/helpers/__init__.py