Metadata-Version: 1.1
Name: pypushover
Version: 0.2.6
Summary: Object Oriented API calls to the Pushover Service
Home-page: https://github.com/KronosKoderS/pypushover
Author: KronoSKoderS
Author-email: superuser.kronos@gmail.com
License: MIT
Download-URL: https://github.com/KronosKoderS/pypushover/tarball/v0.2.6
Platform: UNKNOWN
Classifier: License :: OSI Approved :: MIT License
Classifier: Programming Language :: Python :: 2
Classifier: Programming Language :: Python :: 2.6
Classifier: Programming Language :: Python :: 2.7
Classifier: Programming Language :: Python :: 3
Classifier: Programming Language :: Python :: 3.2
Classifier: Programming Language :: Python :: 3.3
Classifier: Programming Language :: Python :: 3.4
